caltools/__init__.py
caltools/pde.py
caltools-0.1.5.dist-info/METADATA
caltools-0.1.5.dist-info/WHEEL
caltools-0.1.5.dist-info/top_level.txt
caltools-0.1.5.dist-info/RECORD
