Metadata-Version: 2.4
Name: caltools
Version: 0.1.5
Summary: A SymPy-based toolset including PDE classification utilities.
Author-email: manohar100323 <manohar100323@gmail.com>
License: MIT
Project-URL: Homepage, https://github.com/manohar100323/caltools
Project-URL: Bug Tracker, https://github.com/manohar100323/caltools/issues
Keywords: math,sympy,pde,calculus,tools,classification
Requires-Python: >=3.9
Requires-Dist: sympy>=1.10
